seedance_ai_video/__init__.py
seedance_ai_video-1767581.341.557.dist-info/licenses/LICENSE
seedance_ai_video-1767581.341.557.dist-info/METADATA
seedance_ai_video-1767581.341.557.dist-info/WHEEL
seedance_ai_video-1767581.341.557.dist-info/top_level.txt
seedance_ai_video-1767581.341.557.dist-info/RECORD
